README.rst
setup.cfg
setup.py
grg_psse2grg/__init__.py
grg_psse2grg/common.py
grg_psse2grg/exception.py
grg_psse2grg/io.py
grg_psse2grg/struct.py
grg_psse2grg.egg-info/PKG-INFO
grg_psse2grg.egg-info/SOURCES.txt
grg_psse2grg.egg-info/dependency_links.txt
grg_psse2grg.egg-info/requires.txt
grg_psse2grg.egg-info/top_level.txt