Metadata-Version: 1.1
Name: grg-psse2grg
Version: 0.0.2
Summary: Data structures and methods for translating PSSE and GRG data files
Home-page: https://github.com/lanl-ansi/grg-psse2grg
Author: Carleton Coffrin
Author-email: cjc@lanl.gov
License: BSD
Platform: UNKNOWN
Classifier: Development Status :: 4 - Beta
Classifier: Intended Audience :: Developers
Classifier: License :: OSI Approved :: BSD License
Classifier: Operating System :: OS Independent
Classifier: Programming Language :: Python
Classifier: Programming Language :: Python :: 2
Classifier: Programming Language :: Python :: 2.7
Classifier: Programming Language :: Python :: 3
Classifier: Programming Language :: Python :: 3.4
Classifier: Programming Language :: Python :: 3.5
Classifier: Programming Language :: Python :: 3.6
